<powerpagecomponent powerpagecomponentid="327ceb3a-2974-ef11-a670-0022480a5af3">
  <content>{
  "value": "/web-files/Trillora-Banner.png",
  "display_name": "Trillora Logo",
  "type": 756150000
}</content>
  <iscustomizable>1</iscustomizable>
  <name>Trillora Logo</name>
  <powerpagecomponenttype>7</powerpagecomponenttype>
  <powerpagesiteid>
    <powerpagesiteid>025c18df-aa07-44d8-9dad-318b2b4b7216</powerpagesiteid>
  </powerpagesiteid>
  <powerpagesitelanguageid>
    <powerpagesitelanguageid>26202963-026d-48bf-a29e-321f526b4cda</powerpagesitelanguageid>
  </powerpagesitelanguageid>
  <statecode>0</statecode>
  <statuscode>1</statuscode>
</powerpagecomponent>