<powerpagecomponent powerpagecomponentid="a756bd48-c8cc-427b-9259-a23efd416821">
  <content>{"entityname":"adx_webpage","isdefault":false,"rewriteurl":"~/Pages/AccessDenied.aspx","usewebsiteheaderandfooter":true}</content>
  <iscustomizable>1</iscustomizable>
  <name>Access Denied</name>
  <powerpagecomponenttype>6</powerpagecomponenttype>
  <powerpagesiteid>
    <powerpagesiteid>025c18df-aa07-44d8-9dad-318b2b4b7216</powerpagesiteid>
  </powerpagesiteid>
  <statecode>0</statecode>
  <statuscode>1</statuscode>
</powerpagecomponent>